swagger_ui_bundle/__init__.py
swagger_ui_bundle/vendor/swagger-ui-4.15.5/favicon-16x16.png
swagger_ui_bundle/vendor/swagger-ui-4.15.5/favicon-32x32.png
swagger_ui_bundle/vendor/swagger-ui-4.15.5/index.css
swagger_ui_bundle/vendor/swagger-ui-4.15.5/index.html
swagger_ui_bundle/vendor/swagger-ui-4.15.5/index.j2
swagger_ui_bundle/vendor/swagger-ui-4.15.5/oauth2-redirect.html
swagger_ui_bundle/vendor/swagger-ui-4.15.5/swagger-initializer.js
swagger_ui_bundle/vendor/swagger-ui-4.15.5/swagger-ui-bundle.js
swagger_ui_bundle/vendor/swagger-ui-4.15.5/swagger-ui-bundle.js.map
swagger_ui_bundle/vendor/swagger-ui-4.15.5/swagger-ui-es-bundle-core.js
swagger_ui_bundle/vendor/swagger-ui-4.15.5/swagger-ui-es-bundle-core.js.map
swagger_ui_bundle/vendor/swagger-ui-4.15.5/swagger-ui-es-bundle.js
swagger_ui_bundle/vendor/swagger-ui-4.15.5/swagger-ui-es-bundle.js.map
swagger_ui_bundle/vendor/swagger-ui-4.15.5/swagger-ui-standalone-preset.js
swagger_ui_bundle/vendor/swagger-ui-4.15.5/swagger-ui-standalone-preset.js.map
swagger_ui_bundle/vendor/swagger-ui-4.15.5/swagger-ui.css
swagger_ui_bundle/vendor/swagger-ui-4.15.5/swagger-ui.css.map
swagger_ui_bundle/vendor/swagger-ui-4.15.5/swagger-ui.js
swagger_ui_bundle/vendor/swagger-ui-4.15.5/swagger-ui.js.map
swagger_4_ui_bundle-0.0.4.dist-info/LICENSE
swagger_4_ui_bundle-0.0.4.dist-info/METADATA
swagger_4_ui_bundle-0.0.4.dist-info/WHEEL
swagger_4_ui_bundle-0.0.4.dist-info/top_level.txt
swagger_4_ui_bundle-0.0.4.dist-info/RECORD
