Metadata-Version: 2.1
Name: swagger-4-ui-bundle
Version: 0.0.4
Summary: swagger_4_ui_bundle - swagger-ui files in a pip package
Home-page: https://github.com/bartsanchez/swagger_ui_bundle
Author: Daniel Grossmann-Kavanagh, Bartolomé Sánchez Salado
License: Apache License Version 2.0
Keywords: swagger-ui
Classifier: Programming Language :: Python
Classifier: Programming Language :: Python :: 3.7
Classifier: Programming Language :: Python :: 3.8
Classifier: Programming Language :: Python :: 3.9
Classifier: Programming Language :: Python :: 3.10
Classifier: Development Status :: 5 - Production/Stable
Classifier: Intended Audience :: Developers
Classifier: Operating System :: OS Independent
License-File: LICENSE
Requires-Dist: Jinja2 (>=2.0)
